{"proxies":{"ti.audiovisualizerview.AudiovisualizerviewModule":{"superPackageName":"org.appcelerator.kroll","superProxyBindingClassName":"org.appcelerator.kroll.KrollModuleBindingGen","proxyClassName":"AudiovisualizerviewModule","proxyAttrs":{"propertyAccessors":[],"fullAPIName":"Audiovisualizerview","name":"Audiovisualizerview","proxyClassName":"ti.audiovisualizerview.AudiovisualizerviewModule","isTopLevel":false,"id":"ti.audiovisualizerview"},"packageName":"ti.audiovisualizerview","sourceName":"ti.audiovisualizerview.AudiovisualizerviewModuleBindingGen","constants":{"AUDIOSESSION_OUTPUTMIX":{"proxyName":"AUDIOSESSION_OUTPUTMIX","name":"AUDIOSESSION_OUTPUTMIX","type":"int","value":0}},"superProxyClassName":"KrollModule","isModule":true,"genClassName":"AudiovisualizerviewModuleBindingGen"},"ti.audiovisualizerview.ViewProxy":{"superPackageName":"org.appcelerator.titanium.proxy","methods":{"addLineRenderer":{"runOnUiThread":false,"hasInvocation":false,"args":[{"converter":"org.appcelerator.kroll.KrollConverter","defaultValueProvider":"org.appcelerator.kroll.KrollConverter","name":"args","optional":true,"sourceName":"args","type":"org.appcelerator.kroll.KrollDict"}],"apiName":"addLineRenderer","converter":"org.appcelerator.kroll.KrollConverter","defaultValueProvider":"org.appcelerator.kroll.KrollConverter","name":"__default_name__","returnType":"void"},"addBarGraphRenderer":{"runOnUiThread":false,"hasInvocation":false,"args":[{"converter":"org.appcelerator.kroll.KrollConverter","defaultValueProvider":"org.appcelerator.kroll.KrollConverter","name":"d","optional":true,"sourceName":"d","type":"org.appcelerator.kroll.KrollDict"}],"apiName":"addBarGraphRenderer","converter":"org.appcelerator.kroll.KrollConverter","defaultValueProvider":"org.appcelerator.kroll.KrollConverter","name":"__default_name__","returnType":"void"},"clearRenderers":{"runOnUiThread":false,"hasInvocation":false,"args":[],"apiName":"clearRenderers","converter":"org.appcelerator.kroll.KrollConverter","defaultValueProvider":"org.appcelerator.kroll.KrollConverter","name":"__default_name__","returnType":"void"},"release":{"runOnUiThread":false,"hasInvocation":false,"args":[],"apiName":"release","converter":"org.appcelerator.kroll.KrollConverter","defaultValueProvider":"org.appcelerator.kroll.KrollConverter","name":"__default_name__","returnType":"void"},"addCircleRenderer":{"runOnUiThread":false,"hasInvocation":false,"args":[],"apiName":"addCircleRenderer","converter":"org.appcelerator.kroll.KrollConverter","defaultValueProvider":"org.appcelerator.kroll.KrollConverter","name":"__default_name__","returnType":"void"}},"superProxyBindingClassName":"org.appcelerator.titanium.proxy.TiViewProxyBindingGen","proxyClassName":"ViewProxy","proxyAttrs":{"propertyAccessors":[],"fullAPIName":"Audiovisualizerview.View","name":"View","proxyClassName":"ti.audiovisualizerview.ViewProxy","isTopLevel":false,"id":"ti.audiovisualizerview.ViewProxy","creatableInModule":"ti.audiovisualizerview.AudiovisualizerviewModule","parentModule":"org.appcelerator.kroll.annotations.Kroll.DEFAULT"},"packageName":"ti.audiovisualizerview","sourceName":"ti.audiovisualizerview.ViewProxyBindingGen","superProxyClassName":"TiViewProxy","isModule":false,"genClassName":"ViewProxyBindingGen"}},"modules":{"ti.audiovisualizerview.AudiovisualizerviewModule":{"apiName":"Audiovisualizerview","createProxies":[{"propertyAccessors":[],"fullAPIName":"Audiovisualizerview.View","name":"View","proxyClassName":"ti.audiovisualizerview.ViewProxy","isTopLevel":false,"id":"ti.audiovisualizerview.ViewProxy","creatableInModule":"ti.audiovisualizerview.AudiovisualizerviewModule","parentModule":"org.appcelerator.kroll.annotations.Kroll.DEFAULT"}]}}}